async_fetcher/__init__.py
async_fetcher/exceptions.py
async_fetcher/fetch.py
async_fetcher/fetch_result.py
async_fetcher/utils.py
async_fetcher-0.3.6.dist-info/METADATA
async_fetcher-0.3.6.dist-info/RECORD
async_fetcher-0.3.6.dist-info/WHEEL
async_fetcher-0.3.6.dist-info/top_level.txt
tests/__init__.py
tests/server.py
tests/test_fetch_result.py
tests/test_fetcher.py
