Metadata-Version: 2.1
Name: async-fetcher
Version: 0.3.6
Summary: Tiny aiohttp wrapper for http request gathering in sync mode
Home-page: https://github.com/night-crawler/async-fetcher
Author: night-crawler
Author-email: lilo.panic@gmail.com
License: MIT
Platform: UNKNOWN
Classifier: Environment :: Web Environment
Classifier: Intended Audience :: Developers
Classifier: Operating System :: OS Independent
Classifier: Programming Language :: Python
Classifier: Programming Language :: Python :: 3
Classifier: Programming Language :: Python :: 3.6
Classifier: Programming Language :: Python :: 3.7
Classifier: License :: OSI Approved :: MIT License
Requires-Python: >=3.6
Requires-Dist: aiohttp (>=3.3.2)
Requires-Dist: furl
